guess_simulator/__init__.py
guess_simulator/cli.py
guess_simulator/config.py
guess_simulator/game.py
guess_simulator/logger.py
guess_simulator/storage.py
guess_simulator/validator.py
guess_simulator/tests/__init__.py
guess_simulator/tests/test_game.py
guess_simulator/tests/test_integration.py
guess_simulator/tests/test_storage.py
guess_simulator/tests/test_validator.py
guess_simulator-0.1.1.dist-info/licenses/LICENSE
guess_simulator-0.1.1.dist-info/METADATA
guess_simulator-0.1.1.dist-info/WHEEL
guess_simulator-0.1.1.dist-info/entry_points.txt
guess_simulator-0.1.1.dist-info/top_level.txt
guess_simulator-0.1.1.dist-info/RECORD
