Metadata-Version: 2.4
Name: guess-simulator
Version: 0.1.1
Summary: Probability-guided number guessing simulator
Author-email: Amaan <mohdamaan00907@gmail.com>, Nandini Yadav <nandiniyadaventer05@gmail.com>
License: MIT
Project-URL: Homepage, https://github.com/Amaan0907/Probability-Guided-Number-Guessing-Simulator
Keywords: game,guessing,probability,cli,simulator
Classifier: Development Status :: 4 - Beta
Classifier: Intended Audience :: Education
Classifier: License :: OSI Approved :: MIT License
Classifier: Programming Language :: Python :: 3
Classifier: Programming Language :: Python :: 3.7
Classifier: Programming Language :: Python :: 3.8
Classifier: Programming Language :: Python :: 3.9
Classifier: Programming Language :: Python :: 3.10
Classifier: Programming Language :: Python :: 3.11
Classifier: Topic :: Games/Entertainment
Classifier: Topic :: Education
License-File: LICENSE
Dynamic: license-file
